framezip/__init__.py
framezip/core.py
framezip-0.1.0.dist-info/licenses/LICENSE
framezip-0.1.0.dist-info/METADATA
framezip-0.1.0.dist-info/WHEEL
framezip-0.1.0.dist-info/top_level.txt
framezip-0.1.0.dist-info/RECORD
