Metadata-Version: 2.4
Name: framezip
Version: 0.1.0
Summary: Utilities to pack and unpack pandas DataFrames
Home-page: https://github.com/Lairizzle/framezip
Author: Keith Henderson
Author-email: keith.donaldh@gmail.com
Classifier: Programming Language :: Python :: 3
Classifier: License :: OSI Approved :: MIT License
Classifier: Operating System :: OS Independent
Requires-Python: >=3.7
License-File: LICENSE
Requires-Dist: pandas>=1.0
Dynamic: author
Dynamic: author-email
Dynamic: classifier
Dynamic: description
Dynamic: description-content-type
Dynamic: home-page
Dynamic: license-file
Dynamic: requires-dist
Dynamic: requires-python
Dynamic: summary
